arguebuf/__init__.py
arguebuf/dt.py
arguebuf/py.typed
arguebuf/traverse.py
arguebuf/utils.py
arguebuf/cli/__init__.py
arguebuf/cli/__main__.py
arguebuf/cli/app.py
arguebuf/cli/graph.py
arguebuf/cli/model.py
arguebuf/cli/server.py
arguebuf/cli/text.py
arguebuf/cli/translator.py
arguebuf/dump/__init__.py
arguebuf/dump/_config.py
arguebuf/dump/_dump_aif.py
arguebuf/dump/_dump_d2.py
arguebuf/dump/_dump_dict.py
arguebuf/dump/_dump_graphviz.py
arguebuf/dump/_dump_io.py
arguebuf/dump/_dump_json.py
arguebuf/dump/_dump_networkx.py
arguebuf/dump/_dump_path.py
arguebuf/dump/_dump_protobuf.py
arguebuf/dump/_dump_xaif.py
arguebuf/load/__init__.py
arguebuf/load/_config.py
arguebuf/load/_load_aif.py
arguebuf/load/_load_aml.py
arguebuf/load/_load_argdown.py
arguebuf/load/_load_brat.py
arguebuf/load/_load_casebase.py
arguebuf/load/_load_dict.py
arguebuf/load/_load_io.py
arguebuf/load/_load_json.py
arguebuf/load/_load_kialo.py
arguebuf/load/_load_microtexts.py
arguebuf/load/_load_ova.py
arguebuf/load/_load_path.py
arguebuf/load/_load_protobuf.py
arguebuf/load/_load_sadface.py
arguebuf/load/_load_text.py
arguebuf/load/_load_xaif.py
arguebuf/model/__init__.py
arguebuf/model/analyst.py
arguebuf/model/edge.py
arguebuf/model/graph.py
arguebuf/model/metadata.py
arguebuf/model/node.py
arguebuf/model/participant.py
arguebuf/model/reference.py
arguebuf/model/resource.py
arguebuf/model/scheme.py
arguebuf/model/typing.py
arguebuf/model/userdata.py
arguebuf/model/utils.py
arguebuf/render/__init__.py
arguebuf/render/_render_d2.py
arguebuf/render/_render_graphviz.py
arguebuf/schemas/__init__.py
arguebuf/schemas/aif.py
arguebuf/schemas/argdown.py
arguebuf/schemas/d2.py
arguebuf/schemas/graphviz.py
arguebuf/schemas/microtexts.py
arguebuf/schemas/ova.py
arguebuf/schemas/sadface.py
arguebuf/schemas/xaif.py
arguebuf-2.7.2.dist-info/licenses/LICENSE
arguebuf-2.7.2.dist-info/METADATA
arguebuf-2.7.2.dist-info/WHEEL
arguebuf-2.7.2.dist-info/entry_points.txt
arguebuf-2.7.2.dist-info/top_level.txt
arguebuf-2.7.2.dist-info/RECORD
