Metadata-Version: 2.4
Name: arguebuf
Version: 2.7.2
Summary: Create and analyze argument graphs and serialize them via Protobuf
Author-email: Mirko Lenz <mirko@mirkolenz.com>
Project-URL: Repository, https://github.com/recap-utr/arguebuf-python
Project-URL: Documentation, https://arguebuf.readthedocs.io
Project-URL: Issues, https://github.com/recap-utr/arguebuf-python/issues
Project-URL: Changelog, https://github.com/recap-utr/arguebuf-python/releases
Requires-Python: >=3.11
License-File: LICENSE
Requires-Dist: arg-services<2,>=1
Requires-Dist: networkx<4,>=3
Requires-Dist: pendulum<4,>=3
Requires-Dist: graphviz<1,>=0.20
Requires-Dist: lxml<6,>=5
Provides-Extra: all
Requires-Dist: arguebuf[cli,graphviz]; extra == "all"
Provides-Extra: cli
Requires-Dist: typer<1,>=0.9; extra == "cli"
Requires-Dist: deepl<2,>=1; extra == "cli"
Provides-Extra: graphviz
Requires-Dist: pygraphviz<2,>=1; extra == "graphviz"
Dynamic: license-file
